nuiitivet/__init__.py
nuiitivet/_pyinstaller/__init__.py
nuiitivet/_pyinstaller/hook-nuiitivet.py
nuiitivet/animation/__init__.py
nuiitivet/animation/animation.py
nuiitivet/animation/easing.py
nuiitivet/animation/manager.py
nuiitivet/backends/__init__.py
nuiitivet/backends/pyglet/__init__.py
nuiitivet/backends/pyglet/event_loop.py
nuiitivet/backends/pyglet/gpu_frame.py
nuiitivet/backends/pyglet/runner.py
nuiitivet/backends/pyglet/ime/__init__.py
nuiitivet/backends/pyglet/ime/linux.py
nuiitivet/backends/pyglet/ime/macos.py
nuiitivet/backends/pyglet/ime/windows.py
nuiitivet/colors/__init__.py
nuiitivet/colors/names.py
nuiitivet/colors/utils.py
nuiitivet/common/__init__.py
nuiitivet/common/call.py
nuiitivet/common/logging_once.py
nuiitivet/input/__init__.py
nuiitivet/input/codes.py
nuiitivet/input/events.py
nuiitivet/input/pointer.py
nuiitivet/layout/__init__.py
nuiitivet/layout/alignment.py
nuiitivet/layout/column.py
nuiitivet/layout/container.py
nuiitivet/layout/cross_aligned.py
nuiitivet/layout/deck.py
nuiitivet/layout/flow.py
nuiitivet/layout/for_each.py
nuiitivet/layout/gap.py
nuiitivet/layout/grid.py
nuiitivet/layout/layout_engine.py
nuiitivet/layout/layout_utils.py
nuiitivet/layout/measure.py
nuiitivet/layout/metrics.py
nuiitivet/layout/row.py
nuiitivet/layout/scroll_viewport.py
nuiitivet/layout/scroller.py
nuiitivet/layout/spacer.py
nuiitivet/layout/stack.py
nuiitivet/layout/uniform_flow.py
nuiitivet/material/__init__.py
nuiitivet/material/app.py
nuiitivet/material/buttons.py
nuiitivet/material/card.py
nuiitivet/material/dialogs.py
nuiitivet/material/icon.py
nuiitivet/material/intents.py
nuiitivet/material/loading_indicator.py
nuiitivet/material/navigation_rail.py
nuiitivet/material/overlay.py
nuiitivet/material/selection_controls.py
nuiitivet/material/shapes.py
nuiitivet/material/snackbar.py
nuiitivet/material/text.py
nuiitivet/material/text_fields.py
nuiitivet/material/styles/__init__.py
nuiitivet/material/styles/button_style.py
nuiitivet-0.2.0.dist-info/licenses/LICENSE
nuiitivet-0.2.0.dist-info/licenses/LICENSES/material-color-utilities-LICENSE.txt
nuiitivet-0.2.0.dist-info/licenses/LICENSES/pyglet-LICENSE.txt
nuiitivet-0.2.0.dist-info/licenses/LICENSES/pyopengl-LICENSE.txt
nuiitivet-0.2.0.dist-info/licenses/LICENSES/skia-python-LICENSE.txt
nuiitivet-0.2.0.dist-info/METADATA
nuiitivet-0.2.0.dist-info/WHEEL
nuiitivet-0.2.0.dist-info/entry_points.txt
nuiitivet-0.2.0.dist-info/top_level.txt
nuiitivet-0.2.0.dist-info/RECORD
