Metadata-Version: 2.4
Name: nuiitivet
Version: 0.2.0
Summary: Intuitive desktop UI framework for Python
Author-email: Yukinobu Imai <kotatu.kotatu@gmail.com>
License-Expression: Apache-2.0
Project-URL: Changelog, https://github.com/yuksblog/nuiitivet/releases
Project-URL: Documentation, https://yuksblog.github.io/nuiitivet/
Project-URL: Homepage, https://github.com/yuksblog/nuiitivet
Project-URL: Issues, https://github.com/yuksblog/nuiitivet/issues
Project-URL: Repository, https://github.com/yuksblog/nuiitivet
Keywords: ui,desktop,framework,graphics,opengl,skia,material design
Classifier: Intended Audience :: Developers
Classifier: Programming Language :: Python :: 3.10
Classifier: Programming Language :: Python :: 3.11
Classifier: Programming Language :: Python :: 3.12
Classifier: Operating System :: MacOS :: MacOS X
Classifier: Operating System :: POSIX :: Linux
Classifier: Operating System :: Microsoft :: Windows
Classifier: Topic :: Software Development :: Libraries :: Application Frameworks
Requires-Python: >=3.10
License-File: LICENSE
License-File: LICENSES/material-color-utilities-LICENSE.txt
License-File: LICENSES/pyglet-LICENSE.txt
License-File: LICENSES/pyopengl-LICENSE.txt
License-File: LICENSES/skia-python-LICENSE.txt
Requires-Dist: material-color-utilities<=0.2.6
Requires-Dist: pyglet>=2.1.11
Requires-Dist: pyopengl>=3.1.10
Requires-Dist: skia-python>=138.0
Dynamic: license-file
